llama_index/callbacks/honeyhive/__init__.py
llama_index/callbacks/honeyhive/base.py
llama_index_callbacks_honeyhive-0.4.1.dist-info/METADATA
llama_index_callbacks_honeyhive-0.4.1.dist-info/WHEEL
llama_index_callbacks_honeyhive-0.4.1.dist-info/licenses/LICENSE
llama_index_callbacks_honeyhive-0.4.1.dist-info/RECORD
