Metadata-Version: 2.4
Name: llama-index-callbacks-honeyhive
Version: 0.4.1
Summary: llama-index callbacks honeyhive integration
Author-email: Your Name <you@example.com>
License-Expression: MIT
License-File: LICENSE
Requires-Python: <4.0,>=3.9
Requires-Dist: honeyhive<0.2,>=0.1.79
Requires-Dist: llama-index-core<0.15,>=0.13.0
